[
    {
        "id": 1,
        "name": "尚硅谷_韩顺平_Go语言核心编程",
        "subTitle": "全网最详细，最细致的go初级教程",
        "desc": "尚硅谷菁英师资整合业界资源，历时一年，打磨出专注于区块链技术的GO语言视频教程。教程采用真实案例，全面具体可落地，从理论到实践，一步一步将GO核心编程技术、编程思想、底层实现融会贯通，使学习者贴近时代脉搏，做IT互联网时代的弄潮儿。",
        "recommand": 3.5,
        "origin": "尚硅谷",
        "type": 0,
        "category": 5,
        "ispassword": false,
        "iscopy": true,
        "ischeck": true,
        "password": "",
        "checkUrl": "https://leexiaop.github.io/static/mini/docs/resources/尚硅谷_韩顺平_Go语言核心编程.pdf",
        "copyUrl": "https://leexiaop.github.io/static/mini/docs/resources/尚硅谷_韩顺平_Go语言核心编程.pdf"
    },
    {
        "id": 2,
        "name": "黑马前端监控SKD实战，设计前端监控体系",
        "subTitle": "全网最详细，最细致的go初级教程",
        "desc": "尚硅谷菁英师资整合业界资源，历时一年，打磨出专注于区块链技术的GO语言视频教程。教程采用真实案例，全面具体可落地，从理论到实践，一步一步将GO核心编程技术、编程思想、底层实现融会贯通，使学习者贴近时代脉搏，做IT互联网时代的弄潮儿。",
        "recommand": 3.5,
        "origin": "尚硅谷",
        "type": 0,
        "category": 5,
        "ispassword": false,
        "iscopy": true,
        "ischeck": true,
        "password": "",
        "checkUrl": "https://leexiaop.github.io/static/mini/docs/resources/尚硅谷_韩顺平_Go语言核心编程.pdf",
        "copyUrl": "https://leexiaop.github.io/static/mini/docs/resources/尚硅谷_韩顺平_Go语言核心编程.pdf"
    }
]